Hot3nCoder/__init__.py
Hot3nCoder/main.py
Hot3nCoder/math_process.py
Hot3nCoder/src_process.py
Hot3nCoder-1.0.5.dist-info/METADATA
Hot3nCoder-1.0.5.dist-info/WHEEL
Hot3nCoder-1.0.5.dist-info/entry_points.txt
Hot3nCoder-1.0.5.dist-info/top_level.txt
Hot3nCoder-1.0.5.dist-info/RECORD
