Metadata-Version: 2.1
Name: Hot3nCoder
Version: 1.0.5
Summary: Encode your cpp file with whatever you want
Home-page: https://github.com/Jas0ff/Hot3nCoder
Author: Jas0ff
Author-email: jason20021019@gmail.com
License: UNKNOWN
Keywords: cpp,encode,emoji,funny
Platform: UNKNOWN
Classifier: Programming Language :: Python :: 3
Classifier: License :: OSI Approved :: MIT License
